{
  "work_item_id": "BL-005",
  "title": "Context-Bound Approval and Transaction Foundation",
  "description": "Provide one reusable fail-closed transaction, approval, journal, receipt, rollback, recovery, and path-coverage foundation for every governed Enki operation.",
  "status": "complete",
  "sprint_id": "NKS-SPR-005",
  "acceptance_criteria": [
    "Approval evaluation binds execution context, action, subject, content hash, authority, validity, revocation, and transaction identity",
    "AVAILABLE, RESERVED, CONSUMED, and REVOKED states are durable and compare-and-swap safe",
    "Interruption before consumption releases reservation and records rollback",
    "Interruption after consumption recovers only through the same exact transaction without duplicate effects",
    "TEST cannot reach production capability and cross-context replay fails closed",
    "Machine-readable path manifests and automated coverage enforce every declared terminal path"
  ],
  "evidence": [
    {
      "evidence_id": "E-BL5-PR29",
      "kind": "pull-request",
      "reference": "https://github.com/nelsonbridge/media-blitz-os/pull/29",
      "description": "Shared governed transaction and path-completeness implementation."
    },
    {
      "evidence_id": "E-BL5-CI",
      "kind": "test-run",
      "reference": "https://github.com/nelsonbridge/media-blitz-os/actions/runs/29309868310",
      "description": "Final transaction and state-write branch CI passed."
    }
  ],
  "blocked_reason": null,
  "superseded_by": null,
  "updated_at": "2026-07-14T06:20:00Z"
}
